unda/__init__.py
unda/unda.py
unda-1.1.0.3.dist-info/LICENSE
unda-1.1.0.3.dist-info/METADATA
unda-1.1.0.3.dist-info/WHEEL
unda-1.1.0.3.dist-info/top_level.txt
unda-1.1.0.3.dist-info/RECORD
