Metadata-Version: 2.1
Name: unda
Version: 1.1.0.3
Summary: A state-based undo and redo functionality module for Python objects.
Home-page: https://github.com/definite-d/unda
Author: Divine Afam-Ifediogor
Author-email: divineafam@gmail.com
License: UNKNOWN
Project-URL: Bug Tracker, https://github.com/definite-d/unda/issues
Project-URL: Documentation, https://definite-d.github.io/unda/
Platform: UNKNOWN
Classifier: Programming Language :: Python :: 3
Classifier: Programming Language :: Python :: 3.6
Classifier: License :: OSI Approved :: MIT License
Classifier: Operating System :: OS Independent
Requires-Python: >=3.6
License-File: LICENSE
